LICENSE
README.md
setup.py
tiana/__init__.py
tiana/file_organizers/__init__.py
tiana/file_organizers/file_preparing.py
tiana/file_organizers/file_reading.py
tiana/metrics_plotter/__init__.py
tiana/metrics_plotter/metrics_plotting.py
tiana/metrics_plotter/threshold_metrics.py
tiana_sis.egg-info/PKG-INFO
tiana_sis.egg-info/SOURCES.txt
tiana_sis.egg-info/dependency_links.txt
tiana_sis.egg-info/not-zip-safe
tiana_sis.egg-info/requires.txt
tiana_sis.egg-info/top_level.txt